seagull/__init__.py
seagull/board.py
seagull/rules.py
seagull/simulator.py
seagull/lifeforms/__init__.py
seagull/lifeforms/base.py
seagull/lifeforms/custom.py
seagull/lifeforms/gliders.py
seagull/lifeforms/growers.py
seagull/lifeforms/oscillators.py
seagull/lifeforms/random.py
seagull/lifeforms/static.py
seagull/lifeforms/wiki.py
seagull/utils/__init__.py
seagull/utils/statistics.py
pyseagull-1.0.0b4.dist-info/LICENSE
pyseagull-1.0.0b4.dist-info/METADATA
pyseagull-1.0.0b4.dist-info/WHEEL
pyseagull-1.0.0b4.dist-info/top_level.txt
pyseagull-1.0.0b4.dist-info/RECORD
